AboutCode-3.0.0.dev3.dist-info/DESCRIPTION.rst
AboutCode-3.0.0.dev3.dist-info/RECORD
AboutCode-3.0.0.dev3.dist-info/WHEEL
AboutCode-3.0.0.dev3.dist-info/entry_points.txt
AboutCode-3.0.0.dev3.dist-info/metadata.json
AboutCode-3.0.0.dev3.dist-info/LICENSE.txt
AboutCode-3.0.0.dev3.dist-info/top_level.txt
AboutCode-3.0.0.dev3.dist-info/METADATA
about_tool/model.py
about_tool/util.py
about_tool/cmd.py
about_tool/schematics_model.py
about_tool/gen.py
about_tool/attrib.py
about_tool/__init__.py
about_tool/__main__.py
about_tool/api.py
about_tool/saneyaml.py
AboutCode-3.0.0.dev3.data/data/about/about.cfg
AboutCode-3.0.0.dev3.data/data/about/NOTICE
AboutCode-3.0.0.dev3.data/data/about/configure
AboutCode-3.0.0.dev3.data/data/about/configure.bat
AboutCode-3.0.0.dev3.data/data/about/SPEC
AboutCode-3.0.0.dev3.data/data/about/USAGE.rst
AboutCode-3.0.0.dev3.data/data/about/README.rst
AboutCode-3.0.0.dev3.data/data/about/about.ABOUT
AboutCode-3.0.0.dev3.data/data/about/about.bat
AboutCode-3.0.0.dev3.data/data/about/apache-2.0.LICENSE
AboutCode-3.0.0.dev3.data/data/about/about
